LICENSE
MANIFEST.in
README
README.md
setup.cfg
setup.py
pyiArduinoI2Cmotor/__init__.py
pyiArduinoI2Cmotor/iarduino_I2C_Motor.cpp
pyiArduinoI2Cmotor/iarduino_I2C_Motor.h
pyiArduinoI2Cmotor/iarduino_I2C_Motor.pxd
pyiArduinoI2Cmotor/iarduino_I2C_PI.h
pyiArduinoI2Cmotor/pyiArduinoI2Cmotor.cpp
pyiArduinoI2Cmotor/pyiArduinoI2Cmotor.pyx
pyiArduinoI2Cmotor/setup.py
pyiArduinoI2Cmotor.egg-info/PKG-INFO
pyiArduinoI2Cmotor.egg-info/SOURCES.txt
pyiArduinoI2Cmotor.egg-info/dependency_links.txt
pyiArduinoI2Cmotor.egg-info/top_level.txt
pyiArduinoI2Cmotor/cpp/Car.cpp
pyiArduinoI2Cmotor/cpp/FindDevices.cpp
pyiArduinoI2Cmotor/cpp/FindMagnet.cpp
pyiArduinoI2Cmotor/cpp/FindMaxSpeed.cpp
pyiArduinoI2Cmotor/cpp/FindReducer.cpp
pyiArduinoI2Cmotor/cpp/GetError.cpp
pyiArduinoI2Cmotor/cpp/GetInfo.cpp
pyiArduinoI2Cmotor/cpp/GetSpeedM_S.cpp
pyiArduinoI2Cmotor/cpp/GetSpeedPWM.cpp
pyiArduinoI2Cmotor/cpp/GetSpeedRPM.cpp
pyiArduinoI2Cmotor/cpp/GetStop.cpp
pyiArduinoI2Cmotor/cpp/GetSum.cpp
pyiArduinoI2Cmotor/cpp/NewAddress.cpp
pyiArduinoI2Cmotor/cpp/Serial.h
pyiArduinoI2Cmotor/cpp/SetDirection.cpp
pyiArduinoI2Cmotor/cpp/SetError.cpp
pyiArduinoI2Cmotor/cpp/SetSpeedM_S.cpp
pyiArduinoI2Cmotor/cpp/SetSpeedM_S_Stop.cpp
pyiArduinoI2Cmotor/cpp/SetSpeedPWM.cpp
pyiArduinoI2Cmotor/cpp/SetSpeedPWM_Stop.cpp
pyiArduinoI2Cmotor/cpp/SetSpeedRPM.cpp
pyiArduinoI2Cmotor/cpp/SetSpeedRPM_Stop.cpp
pyiArduinoI2Cmotor/cpp/SetStopNeutral.cpp
pyiArduinoI2Cmotor/examples/Car.py
pyiArduinoI2Cmotor/examples/FindDevices.py
pyiArduinoI2Cmotor/examples/FindMagnet.py
pyiArduinoI2Cmotor/examples/FindMaxSpeed.py
pyiArduinoI2Cmotor/examples/FindReducer.py
pyiArduinoI2Cmotor/examples/GetError.py
pyiArduinoI2Cmotor/examples/GetInfo.py
pyiArduinoI2Cmotor/examples/GetSpeedM_S.py
pyiArduinoI2Cmotor/examples/GetSpeedPWM.py
pyiArduinoI2Cmotor/examples/GetSpeedRPM.py
pyiArduinoI2Cmotor/examples/GetStop.py
pyiArduinoI2Cmotor/examples/GetSum.py
pyiArduinoI2Cmotor/examples/SetDirection.py
pyiArduinoI2Cmotor/examples/SetError.py
pyiArduinoI2Cmotor/examples/SetSpeedM_S.py
pyiArduinoI2Cmotor/examples/SetSpeedM_S_Stop.py
pyiArduinoI2Cmotor/examples/SetSpeedPWM.py
pyiArduinoI2Cmotor/examples/SetSpeedPWM_Stop.py
