Metadata-Version: 2.1
Name: pyiArduinoI2Cmotor
Version: 0.0.4
Summary: iarduino.ru module for Raspberry Pi
Home-page: http://github.com/tremaru/pyiArduinoI2Cmotor
Author: iarduino.ru
Author-email: shop@iarduino.ru
License: MIT
Classifier: Programming Language :: Python :: 3
License-File: LICENSE
